odoo/addons/website_sale_restrict_by_pricelist/README.rst
odoo/addons/website_sale_restrict_by_pricelist/__init__.py
odoo/addons/website_sale_restrict_by_pricelist/__manifest__.py
odoo/addons/website_sale_restrict_by_pricelist/controllers/__init__.py
odoo/addons/website_sale_restrict_by_pricelist/controllers/main.py
odoo/addons/website_sale_restrict_by_pricelist/i18n/es.po
odoo/addons/website_sale_restrict_by_pricelist/i18n/website_sale_restrict_by_pricelist.pot
odoo/addons/website_sale_restrict_by_pricelist/models/__init__.py
odoo/addons/website_sale_restrict_by_pricelist/models/res_config_settings.py
odoo/addons/website_sale_restrict_by_pricelist/models/res_partner.py
odoo/addons/website_sale_restrict_by_pricelist/readme/CONTRIBUTORS.md
odoo/addons/website_sale_restrict_by_pricelist/readme/DESCRIPTION.md
odoo/addons/website_sale_restrict_by_pricelist/readme/USAGE.md
odoo/addons/website_sale_restrict_by_pricelist/static/description/icon.png
odoo/addons/website_sale_restrict_by_pricelist/static/description/icon.svg
odoo/addons/website_sale_restrict_by_pricelist/static/description/index.html
odoo/addons/website_sale_restrict_by_pricelist/tests/__init__.py
odoo/addons/website_sale_restrict_by_pricelist/tests/test_restrict_partner_product.py
odoo/addons/website_sale_restrict_by_pricelist/views/res_config_settings_views.xml
odoo/addons/website_sale_restrict_by_pricelist/views/res_partner_views.xml
odoo_addon_website_sale_restrict_by_pricelist-15.0.1.0.0.2.dist-info/METADATA
odoo_addon_website_sale_restrict_by_pricelist-15.0.1.0.0.2.dist-info/WHEEL
odoo_addon_website_sale_restrict_by_pricelist-15.0.1.0.0.2.dist-info/top_level.txt
odoo_addon_website_sale_restrict_by_pricelist-15.0.1.0.0.2.dist-info/RECORD
